shub_workflow/__init__.py
shub_workflow/base.py
shub_workflow/crawl.py
shub_workflow/py.typed
shub_workflow/script.py
shub_workflow/contrib/__init__.py
shub_workflow/contrib/hubstorage.py
shub_workflow/contrib/sentry.py
shub_workflow/contrib/slack.py
shub_workflow/deliver/__init__.py
shub_workflow/deliver/base.py
shub_workflow/graph/__init__.py
shub_workflow/graph/task.py
shub_workflow/graph/utils.py
shub_workflow/issuer/__init__.py
shub_workflow/utils/__init__.py
shub_workflow/utils/alert_sender.py
shub_workflow/utils/clone_job.py
shub_workflow/utils/contexts.py
shub_workflow/utils/dupefilter.py
shub_workflow/utils/futils.py
shub_workflow/utils/gcstorage.py
shub_workflow/utils/monitor.py
shub_workflow/utils/scanjobs.py
shub_workflow/utils/sesemail.py
shub_workflow/utils/watchdog.py
tests/__init__.py
tests/test_base_manager.py
tests/test_crawl_manager.py
tests/test_futils.py
tests/test_graph_manager.py
tests/test_typing.py
shub_workflow-1.14.31.1.dist-info/LICENSE
shub_workflow-1.14.31.1.dist-info/METADATA
shub_workflow-1.14.31.1.dist-info/WHEEL
shub_workflow-1.14.31.1.dist-info/top_level.txt
shub_workflow-1.14.31.1.dist-info/RECORD
