Metadata-Version: 2.1
Name: shub-workflow
Version: 1.14.31.1
Summary: Workflow manager for Zyte ScrapyCloud tasks.
Home-page: https://github.com/scrapinghub/shub-workflow
Maintainer: Scrapinghub
License: BSD
Classifier: Development Status :: 5 - Production/Stable
Classifier: Intended Audience :: Developers
Classifier: License :: OSI Approved :: BSD License
Classifier: Operating System :: OS Independent
Classifier: Programming Language :: Python :: 3.9
Classifier: Programming Language :: Python :: 3.10
Classifier: Programming Language :: Python :: 3.11
License-File: LICENSE
Requires-Dist: pyyaml>=3.12
Requires-Dist: scrapinghub[msgpack]>=2.3.1
Requires-Dist: jinja2>=2.7.3
Requires-Dist: sqlitedict==2.1.0
Requires-Dist: boto3>=1.9.92
Requires-Dist: bloom-filter2==2.0.0
Requires-Dist: collection-scanner
Requires-Dist: tenacity
Requires-Dist: typing-extensions
Requires-Dist: scrapy
Requires-Dist: prettytable
Requires-Dist: jmespath
Requires-Dist: timelength
Provides-Extra: with-s3-tools
Requires-Dist: s3fs>=0.4.0; extra == "with-s3-tools"
Provides-Extra: with-gcs-tools
Requires-Dist: google-cloud-storage>=1.38.0; extra == "with-gcs-tools"
